pyarmor_runtime_000000/__init__.py
pyarmor_runtime_000000/pyarmor_runtime.pyd
siem_hkm_ai_smartcore/__init__.py
siem_hkm_ai_smartcore/auth/__init__.py
siem_hkm_ai_smartcore/auth/auth.py
siem_hkm_ai_smartcore/core/__init__.py
siem_hkm_ai_smartcore/core/ahu_optimizer/__init__.py
siem_hkm_ai_smartcore/core/ahu_optimizer/ahu_optimizer.py
siem_hkm_ai_smartcore/core/chiller_optimizer/__init__.py
siem_hkm_ai_smartcore/interfaces/__init__.py
siem_hkm_ai_smartcore/interfaces/bacnet_comm/__init__.py
siem_hkm_ai_smartcore/interfaces/bacnet_comm/bacnet_device.py
siem_hkm_ai_smartcore/interfaces/opcua_device/__init__.py
siem_hkm_ai_smartcore/interfaces/opcua_device/opcua_uses.py
siem_hkm_ai_smartcore/interfaces/sensor_data_adapter/__init__.py
siem_hkm_ai_smartcore/utils/__init__.py
siem_hkm_ai_smartcore/utils/doc_access.py
siem_hkm_ai_smartcore-1.0.2.dist-info/METADATA
siem_hkm_ai_smartcore-1.0.2.dist-info/WHEEL
siem_hkm_ai_smartcore-1.0.2.dist-info/top_level.txt
siem_hkm_ai_smartcore-1.0.2.dist-info/RECORD
