Metadata-Version: 2.1
Name: siem-hkm-ai-smartcore
Version: 1.0.2
Summary: A Python library for intelligent building management with BACnet/OPC UA communication and HVAC optimization
Home-page: UNKNOWN
Author: lanzco's team
License: MIT
Platform: UNKNOWN
Classifier: Programming Language :: Python :: 3
Classifier: License :: OSI Approved :: MIT License
Classifier: Operating System :: OS Independent
Classifier: Intended Audience :: Developers
Classifier: Intended Audience :: System Administrators
Classifier: Topic :: Home Automation
Classifier: Topic :: Software Development :: Libraries :: Python Modules
Requires-Dist: aiosqlite==0.21.0
Requires-Dist: BAC0==2025.8.16
Requires-Dist: bacpypes3==0.0.102
Requires-Dist: cffi==1.17.1
Requires-Dist: colorama==0.4.6
Requires-Dist: contourpy==1.3.0
Requires-Dist: cryptography==45.0.6
Requires-Dist: cycler==0.12.1
Requires-Dist: docutils==0.22
Requires-Dist: fonttools==4.59.2
Requires-Dist: importlib-resources==6.5.2
Requires-Dist: joblib==1.5.2
Requires-Dist: kiwisolver==1.4.7
Requires-Dist: llvmlite==0.43.0
Requires-Dist: lxml==6.0.1
Requires-Dist: matplotlib==3.9.4
Requires-Dist: numba==0.60.0
Requires-Dist: numpy==2.0.2
Requires-Dist: opcua==0.98.13
Requires-Dist: packaging==25.0
Requires-Dist: pandas==2.3.2
Requires-Dist: pillow==11.3.0
Requires-Dist: pyarmor==9.1.8
Requires-Dist: pyarmor.cli.core==7.6.7
Requires-Dist: pycparser==2.22
Requires-Dist: pyparsing==3.2.3
Requires-Dist: pythermalcomfort==3.3.0
Requires-Dist: python-dateutil==2.9.0.post0
Requires-Dist: python-dotenv==1.1.1
Requires-Dist: pytz==2025.2
Requires-Dist: scikit-learn==1.6.1
Requires-Dist: scipy==1.13.1
Requires-Dist: seaborn==0.13.2
Requires-Dist: six==1.17.0
Requires-Dist: threadpoolctl==3.6.0
Requires-Dist: tqdm==4.67.1
Requires-Dist: typing-extensions==4.15.0
Requires-Dist: tzdata==2025.2
Requires-Dist: xgboost==2.1.4
Requires-Dist: zipp==3.23.0
